README.txt
setup.py
collective/__init__.py
collective.js.s3slider.egg-info/PKG-INFO
collective.js.s3slider.egg-info/SOURCES.txt
collective.js.s3slider.egg-info/dependency_links.txt
collective.js.s3slider.egg-info/entry_points.txt
collective.js.s3slider.egg-info/namespace_packages.txt
collective.js.s3slider.egg-info/not-zip-safe
collective.js.s3slider.egg-info/requires.txt
collective.js.s3slider.egg-info/top_level.txt
collective/js/__init__.py
collective/js/s3slider/__init__.py
collective/js/s3slider/configure.zcml
collective/js/s3slider/s3Slider.css
collective/js/s3slider/s3Slider.js
collective/js/s3slider/s3SliderPacked.js
collective/js/s3slider/profiles/default/jsregistry.xml
collective/js/s3slider/profiles/default/metadata.xml
collective/js/s3slider/tests/__init__.py
collective/js/s3slider/tests/base.py
collective/js/s3slider/tests/test_setup.py
docs/HISTORY.txt