Metadata-Version: 1.0
Name: collective.js.s3slider
Version: 1.1
Summary: The s3Slider jQuery plugin is jd`s smooth slide show implementation with jquery
Home-page: https://svn.plone.org/svn/collective/collective.js.s3slider
Author: JeanMichel FRANCOIS aka toutpt
Author-email: jeanmichel.francois@makina-corpus.com
License: GPL
Platform: UNKNOWN
Classifier: Programming Language :: Python
